tetra/trust_main.py
tetra_textual_trust_analyzer-0.1.1.dist-info/LICENSE
tetra_textual_trust_analyzer-0.1.1.dist-info/METADATA
tetra_textual_trust_analyzer-0.1.1.dist-info/WHEEL
tetra_textual_trust_analyzer-0.1.1.dist-info/RECORD
