Metadata-Version: 2.1
Name: tetra-textual-trust-analyzer
Version: 0.1.1
Summary: TETRA: TExtual TRust Analyzer
Home-page: https://github.com/simonamazzarino/TETRA
License: "GPL"
Author: Simona Mazzarino
Author-email: simona.mazzarino@gmail.com
Requires-Python: >=3.11,<4.0
Classifier: License :: Other/Proprietary License
Classifier: Programming Language :: Python :: 3
Classifier: Programming Language :: Python :: 3.11
Requires-Dist: google-api-python-client (>=2.130.0,<3.0.0)
Requires-Dist: nltk (>=3.8.1,<4.0.0)
Requires-Dist: pandas (>=2.2.2,<3.0.0)
Requires-Dist: presidio-analyzer (>=2.2.354,<3.0.0)
Requires-Dist: presidio-anonymizer (>=2.2.354,<3.0.0)
Requires-Dist: sentence-transformers (>=2.7.0,<3.0.0)
Project-URL: Repository, https://github.com/simonamazzarino/TETRA
